arithpy.py
arithpy-0.0.1.dist-info/LICENSE.txt
arithpy-0.0.1.dist-info/METADATA
arithpy-0.0.1.dist-info/WHEEL
arithpy-0.0.1.dist-info/top_level.txt
arithpy-0.0.1.dist-info/RECORD
