Metadata-Version: 2.1
Name: arithpy
Version: 0.0.1
Summary: ArithPy is a simple and easy to use python moduloe made for basic arithmetic operations. The main purpose of creating such python module is to help developers to do calculations quickly in their programs made made by two school going students Suresh Mishra and Sai Binayak Biswal.
Home-page: UNKNOWN
Author: Suresh Mishra
License: UNKNOWN
Platform: UNKNOWN
Classifier: Programming Language :: Python :: 3
Classifier: License :: OSI Approved :: MIT License
Classifier: Operating System :: OS Independent
Requires-Python: >=3.6
